wpinet/__init__.py
wpinet/py.typed
wpinet/version.py
wpinet/src/main.cpp
wpinet/_init__wpinet.py
wpinet/_wpinet.cp312-win_amd64.lib
wpinet/_wpinet.cp312-win_amd64.pyd
wpinet/_wpinet.pyi
wpinet/wpinet.pc
wpinet/trampolines/wpi__PortForwarder.hpp
wpinet/trampolines/wpi__WebServer.hpp
robotpy_wpinet-2025.3.2.3.dist-info/METADATA
robotpy_wpinet-2025.3.2.3.dist-info/WHEEL
robotpy_wpinet-2025.3.2.3.dist-info/entry_points.txt
robotpy_wpinet-2025.3.2.3.dist-info/RECORD
