Metadata-Version: 2.4
Name: robotpy-wpinet
Version: 2025.3.2.3
Summary: Binary wrapper for FRC wpinet library
Project-URL: Source code, https://github.com/robotpy/mostrobotpy
Author-email: RobotPy Development Team <robotpy@googlegroups.com>
License-Expression: BSD-3-Clause
Requires-Dist: robotpy-native-wpinet==2025.3.2
Requires-Dist: robotpy-wpiutil==2025.3.2.3
